Metadata-Version: 2.1
Name: f-task-5-test
Version: 0.0.1
Summary: My Package
Author: Michail
Author-email: mi.ershov.2017@yandex.ru
